{
    "wallpaper": "/home/om/media/pics/wall/turner_study-of-sea.jpg",
    "alpha": "100",
    "special": {
        "background": "#020101",
        "foreground": "#dbd7c6",
        "cursor": "#dbd7c6"
    },
    "colors": {
        "color0": "#020101",
        "color1": "#A59D7C",
        "color2": "#7A8982",
        "color3": "#929687",
        "color4": "#A5A28E",
        "color5": "#ABA88E",
        "color6": "#C6BCA2",
        "color7": "#dbd7c6",
        "color8": "#99968a",
        "color9": "#A59D7C",
        "color10": "#7A8982",
        "color11": "#929687",
        "color12": "#A5A28E",
        "color13": "#ABA88E",
        "color14": "#C6BCA2",
        "color15": "#dbd7c6"
    }
}